bibextract-0.1.1.dist-info/METADATA
bibextract-0.1.1.dist-info/WHEEL
bibextract-0.1.1.dist-info/licenses/LICENSE
bibextract/__init__.py
bibextract/bibextract.cp313-win_amd64.pyd
bibextract/bibextract.pyi
bibextract-0.1.1.dist-info/RECORD
