Metadata-Version: 2.4
Name: bibextract
Version: 0.1.1
Classifier: Intended Audience :: Science/Research
Classifier: License :: OSI Approved :: MIT License
Classifier: Programming Language :: Rust
Classifier: Programming Language :: Python :: 3
Classifier: Programming Language :: Python :: 3.8
Classifier: Programming Language :: Python :: 3.9
Classifier: Programming Language :: Python :: 3.10
Classifier: Programming Language :: Python :: 3.11
Classifier: Programming Language :: Python :: 3.12
Classifier: Programming Language :: Rust
Classifier: Programming Language :: Python :: Implementation :: CPython
Classifier: Programming Language :: Python :: Implementation :: PyPy
Classifier: Topic :: Scientific/Engineering
Classifier: Topic :: Text Processing :: Markup :: LaTeX
Requires-Dist: pytest ; extra == 'dev'
Requires-Dist: pytest-cov ; extra == 'dev'
Requires-Dist: maturin ; extra == 'dev'
Provides-Extra: dev
License-File: LICENSE
Summary: Extract survey content and bibliography from arXiv papers
Keywords: arxiv,latex,bibliography,survey,research,mcp
Author-email: Gautier Dagan <gautier.dagan@gmail.com>
License: MIT
Requires-Python: >=3.8
Project-URL: Homepage, https://github.com/gautierdag/bibextract
Project-URL: Repository, https://github.com/gautierdag/bibextract
Project-URL: Issues, https://github.com/gautierdag/bibextract/issues
